ldap2pg/__init__.py
ldap2pg/config.py
ldap2pg/defaults.py
ldap2pg/format.py
ldap2pg/inspector.py
ldap2pg/ldap.py
ldap2pg/manager.py
ldap2pg/privilege.py
ldap2pg/psql.py
ldap2pg/role.py
ldap2pg/script.py
ldap2pg/utils.py
ldap2pg/validators.py
ldap2pg-5.9.dist-info/AUTHORS.md
ldap2pg-5.9.dist-info/LICENSE
ldap2pg-5.9.dist-info/METADATA
ldap2pg-5.9.dist-info/WHEEL
ldap2pg-5.9.dist-info/entry_points.txt
ldap2pg-5.9.dist-info/top_level.txt
ldap2pg-5.9.dist-info/RECORD
