Metadata-Version: 2.1
Name: ldap2pg
Version: 5.9
Summary: Manage PostgreSQL roles and privileges from YAML or LDAP
Home-page: https://labs.dalibo.com/ldap2pg
Author: Dalibo
Author-email: contact@dalibo.com
License: PostgreSQL
Project-URL: Documentation, https://ldap2pg.rtfd.io/
Project-URL: Tracker, https://github.com/dalibo/ldap2pg/issues
Project-URL: Sources, https://github.com/dalibo/ldap2pg
Classifier: License :: OSI Approved
Classifier: Programming Language :: Python :: 2
Classifier: Programming Language :: Python :: 2.6
Classifier: Programming Language :: Python :: 2.7
Classifier: Programming Language :: Python :: 3
Classifier: Programming Language :: Python :: 3.4
License-File: LICENSE
License-File: AUTHORS.md
Requires-Dist: python-ldap
Requires-Dist: pyyaml
